[
  {
    "id": 1788,
    "name": "Kougra",
    "image": "https://vignette.wikia.nocookie.net/guilds/images/7/76/Blue_kougra.png/revision/latest?cb=20170625062621"
  },
  {
    "id": 2128,
    "name": "Usul",
    "image": "https://vignette.wikia.nocookie.net/guilds/images/f/f8/Usul_green.png/revision/latest?cb=20180708212729"
  },
  {
    "id": 17179,
    "name": "Aisha",
    "image": "https://vignette.wikia.nocookie.net/guilds/images/8/89/Aisha.gif/revision/latest?cb=20180716220804"
  },
  {
    "id": 17181,
    "name": "Bori",
    "image": "https://vignette.wikia.nocookie.net/guilds/images/b/b0/Bori.gif/revision/latest?cb=20180717053816"
  },
  {
    "id": 17174,
    "name": "Cybunny",
    "image": "https://vignette.wikia.nocookie.net/guilds/images/9/91/Cybunny.gif/revision/latest?cb=20180717060017"
  },
  {
    "id": 17177,
    "name": "Eyrie",
    "image": "https://vignette.wikia.nocookie.net/guilds/images/0/0a/Eyrie.gif/revision/latest?cb=20180717063414"
  },
  {
    "id": 17170,
    "name": "Bruce",
    "image": "https://vignette.wikia.nocookie.net/guilds/images/a/ac/Bruce.gif/revision/latest?cb=20180711071529"
  },
  {
    "id": 17173,
    "name": "Chomby",
    "image": "https://vignette.wikia.nocookie.net/guilds/images/6/6c/Chomby.gif/revision/latest?cb=20180717054716"
  },
  {
    "id": 17175,
    "name": "Draik",
    "image": "https://vignette.wikia.nocookie.net/guilds/images/1/1e/4_%289%29.png/revision/latest?cb=20170624165318"
  },
  {
    "id": 2049,
    "name": "Skeith",
    "image": "https://vignette.wikia.nocookie.net/guilds/images/d/d6/Skeith.png/revision/latest?cb=20180509050538"
  },
  {
    "id": 1943,
    "name": "Techo",
    "image": "https://vignette.wikia.nocookie.net/guilds/images/6/61/Techo.gif/revision/latest?cb=20180726222444"
  },
  {
    "id": 17172,
    "name": "Chia",
    "image": "https://vignette.wikia.nocookie.net/guilds/images/c/c8/Blue_chia.png/revision/latest?cb=20170625204020"
  },
  {
    "id": 17171,
    "name": "Buzz",
    "image": "https://vignette.wikia.nocookie.net/guilds/images/5/52/Blue_buzz.png/revision/latest?cb=20170625202437"
  },
  {
    "id": 17176,
    "name": "Elephante",
    "image": "https://vignette.wikia.nocookie.net/guilds/images/5/58/Elephante.gif/revision/latest?cb=20180717062124"
  },
  {
    "id": 1618,
    "name": "Zafara",
    "image": "https://vignette.wikia.nocookie.net/guilds/images/e/ed/Green_zafara.png/revision/latest?cb=20180617030228"
  },
  {
    "id": 17160,
    "name": "Gelert",
    "image": "https://vignette.wikia.nocookie.net/guilds/images/8/82/Gelert.gif/revision/latest?cb=20180609033424"
  },
  {
    "id": 17166,
    "name": "JubJub",
    "image": "https://vignette.wikia.nocookie.net/guilds/images/a/a9/Jubjub.gif/revision/latest?cb=20180729034132"
  },
  {
    "id": 17159,
    "name": "Kau",
    "image": "https://vignette.wikia.nocookie.net/guilds/images/e/ee/Kau.gif/revision/latest?cb=20180811162632"
  },
  {
    "id": 17165,
    "name": "Jetsam",
    "image": "https://vignette.wikia.nocookie.net/guilds/images/e/e5/Blue_jetsam.png/revision/latest?cb=20170625002225"
  },
  {
    "id": 17931,
    "name": "Vandagyre",
    "image": "https://vignette.wikia.nocookie.net/guilds/images/e/ec/VandagyreBlue.png/revision/latest?cb=20141115004842"
  },
  {
    "id": 17162,
    "name": "Grarrl",
    "image": "https://vignette.wikia.nocookie.net/guilds/images/d/d0/Grarrl.gif/revision/latest?cb=20180717073853"
  },
  {
    "id": 1922,
    "name": "Tonu",
    "image": "https://vignette.wikia.nocookie.net/guilds/images/f/fc/Tonu_green.png/revision/latest?cb=20180619214328"
  },
  {
    "id": 17161,
    "name": "Gnorbu",
    "image": "https://vignette.wikia.nocookie.net/guilds/images/6/61/Gnorbu_%281%29.gif/revision/latest?cb=20180717064211"
  },
  {
    "id": 1623,
    "name": "Hissi",
    "image": "https://vignette.wikia.nocookie.net/guilds/images/f/f5/Hissi.gif/revision/latest?cb=20150908002113"
  },
  {
    "id": 17178,
    "name": "Blumaroo",
    "image": "https://vignette.wikia.nocookie.net/guilds/images/4/4b/Blumaroo.gif/revision/latest?cb=20180717053416"
  },
  {
    "id": 17156,
    "name": "Koi",
    "image": "https://vignette.wikia.nocookie.net/guilds/images/9/9a/Blue_koi.png/revision/latest?cb=20170625061007"
  },
  {
    "id": 17163,
    "name": "Grundo",
    "image": "https://vignette.wikia.nocookie.net/guilds/images/4/44/Grundo.gif/revision/latest?cb=20180719024108"
  },
  {
    "id": 2079,
    "name": "Ogrin",
    "image": "https://vignette.wikia.nocookie.net/guilds/images/0/02/Ogrin.gif/revision/latest?cb=20150322003656"
  },
  {
    "id": 1932,
    "name": "Korbat",
    "image": "https://vignette.wikia.nocookie.net/guilds/images/b/bf/Blue_bat.png/revision/latest?cb=20170625062013"
  },
  {
    "id": 1909,
    "name": "Kyrii",
    "image": "https://vignette.wikia.nocookie.net/guilds/images/0/0f/Kyrii.gif/revision/latest?cb=20190120164451"
  },
  {
    "id": 17169,
    "name": "Flotsam",
    "image": "https://vignette.wikia.nocookie.net/guilds/images/9/95/Flotsam.gif/revision/latest?cb=20180609033139"
  },
  {
    "id": 2143,
    "name": "Lenny",
    "image": "https://vignette.wikia.nocookie.net/guilds/images/6/6d/Blue_lenny.png/revision/latest?cb=20170626170315"
  },
  {
    "id": 1931,
    "name": "Pteri",
    "image": "https://vignette.wikia.nocookie.net/guilds/images/e/ed/Pteri.gif/revision/latest?cb=20150308212904"
  },
  {
    "id": 1609,
    "name": "Peophin",
    "image": "https://vignette.wikia.nocookie.net/guilds/images/2/24/Cloud_Peophin.png/revision/latest/scale-to-width-down/200?cb=20120422080711"
  },
  {
    "id": 17167,
    "name": "Kacheek",
    "image": "https://vignette.wikia.nocookie.net/guilds/images/a/a9/Kacheek.gif/revision/latest?cb=20180729051741"
  },
  {
    "id": 2114,
    "name": "Lutari",
    "image": " https://vignette.wikia.nocookie.net/guilds/images/4/4d/Lutari2.gif/revision/latest?cb=20150416212210"
  },
  {
    "id": 1791,
    "name": "Lupe",
    "image": "https://vignette.wikia.nocookie.net/guilds/images/4/43/Lupe.gif/revision/latest?cb=20150218002803"
  },
  {
    "id": 2006,
    "name": "Quiggle",
    "image": "https://vignette.wikia.nocookie.net/guilds/images/8/8d/Yellow_Quiggle.gif/revision/latest?cb=20161126202946"
  },
  {
    "id": 2154,
    "name": "Moehog",
    "image": "https://vignette.wikia.nocookie.net/guilds/images/4/43/Moehog.gif/revision/latest?cb=20150224223816"
  },
  {
    "id": 1946,
    "name": "Krawk",
    "image": "https://vignette.wikia.nocookie.net/guilds/images/0/01/Blue_krawk.png/revision/latest?cb=20170625193224"
  },
  {
    "id": 2048,
    "name": "Meerca",
    "image": "https://vignette.wikia.nocookie.net/guilds/images/8/85/Meerca.gif/revision/latest?cb=20150313204644"
  },
  {
    "id": 17164,
    "name": "Ixi",
    "image": "https://vignette.wikia.nocookie.net/guilds/images/9/90/Ixi_%281%29.gif/revision/latest?cb=20180720003328"
  },
  {
    "id": 2080,
    "name": "Wocky",
    "image": "https://vignette.wikia.nocookie.net/guilds/images/7/7e/Wocky123.gif/revision/latest?cb=20120108162422"
  },
  {
    "id": 1608,
    "name": "Scorchio",
    "image": "https://vignette.wikia.nocookie.net/guilds/images/4/40/Scorchio.gif/revision/latest?cb=20150304014754"
  },
  {
    "id": 2039,
    "name": "Ruki",
    "image": "https://vignette.wikia.nocookie.net/guilds/images/a/ae/Ruki.gif/revision/latest?cb=20150814005516"
  },
  {
    "id": 1921,
    "name": "Poogle",
    "image": "https://vignette.wikia.nocookie.net/guilds/images/c/c0/Red_Poogle.jpg/revision/latest?cb=20140619222138"
  },
  {
    "id": 1604,
    "name": "Uni",
    "image": "https://vignette.wikia.nocookie.net/guilds/images/9/95/Uni.gif/revision/latest?cb=20190302035148"
  },
  {
    "id": 2156,
    "name": "Tuskaninny",
    "image": "https://vignette.wikia.nocookie.net/guilds/images/8/87/Tuskaninny.gif/revision/latest?cb=20150816021521"
  },
  {
    "id": 17180,
    "name": "Acara",
    "image": "https://vignette.wikia.nocookie.net/guilds/images/1/17/Acara.gif/revision/latest?cb=20180629035021"
  },
  {
    "id": 17168,
    "name": "Kiko",
    "image": "https://vignette.wikia.nocookie.net/guilds/images/0/04/Kiko.gif/revision/latest?cb=20180831011328"
  },
  {
    "id": 1940,
    "name": "Xweetok",
    "image": "https://vignette.wikia.nocookie.net/guilds/images/5/5e/Xweetok01.gif/revision/latest?cb=20151021234801"
  },
  {
    "id": 1910,
    "name": "Mynci",
    "image": "https://vignette.wikia.nocookie.net/guilds/images/f/f5/Mynci.gif/revision/latest?cb=20150320222915"
  },
  {
    "id": 1942,
    "name": "Nimmo",
    "image": "https://vignette.wikia.nocookie.net/guilds/images/c/cb/Nimmo.gif/revision/latest?cb=20150220213311"
  }
]
